iflow_mcp_ppt_translator-1.0.5.dist-info/licenses/LICENSE
ppt_translator/__init__.py
ppt_translator/bedrock_client.py
ppt_translator/cli.py
ppt_translator/config.py
ppt_translator/dependencies.py
ppt_translator/post_processing.py
ppt_translator/ppt_handler.py
ppt_translator/prompts.py
ppt_translator/text_utils.py
ppt_translator/translation_engine.py
iflow_mcp_ppt_translator-1.0.5.dist-info/METADATA
iflow_mcp_ppt_translator-1.0.5.dist-info/WHEEL
iflow_mcp_ppt_translator-1.0.5.dist-info/entry_points.txt
iflow_mcp_ppt_translator-1.0.5.dist-info/top_level.txt
iflow_mcp_ppt_translator-1.0.5.dist-info/RECORD
