Metadata-Version: 2.4
Name: iflow-mcp_ppt-translator
Version: 1.0.5
Summary: PowerPoint Translator using Amazon Bedrock
Requires-Python: >=3.11
License-File: LICENSE
Requires-Dist: boto3>=1.40.21
Requires-Dist: click>=8.2.1
Requires-Dist: fastmcp>=2.11.3
Requires-Dist: python-dotenv>=1.1.1
Requires-Dist: python-pptx>=1.0.2
Dynamic: license-file
